dfl/__init__.py
dfl/utils2_Draft.py
dfl_utils/__init__.py
dfl_utils/utils2_Draft.py
dfl_utils-1.8.6.dist-info/METADATA
dfl_utils-1.8.6.dist-info/WHEEL
dfl_utils-1.8.6.dist-info/top_level.txt
dfl_utils-1.8.6.dist-info/RECORD
