Metadata-Version: 2.1
Name: dfl_utils
Version: 1.8.6
Summary: A Powerful Windows-PC-Wechat automation Tool
License: Apache-2.0
Keywords: rpa,windows,wechat,automation
